{
  "wk_000000150": {
    "workId": "wk_000000150",
    "title": "어벤져스: 엔드게임",
    "category": "movie",
    "domain": "generalCulture",
    "creator": "루소 형제",
    "releaseYear": 2019,
    "tags": [
      "히어로",
      "액션",
      "SF",
      "MCU"
    ],
    "legacyIds": [
      "gen_movie_avengers-endgame_2019"
    ],
    "externalIds": {
      "wikidata": "Q23781191"
    },
    "extensions": {
      "ingestChannel": "manual_wikidata",
      "ingestSource": "manual"
    },
    "qualitySignals": {
      "externalIdVerified": true
    }
  },
  "wk_000000984": {
    "workId": "wk_000000984",
    "title": "위플래쉬",
    "category": "movie",
    "domain": "subculture",
    "externalIds": {
      "wikidata": "Q100803056"
    },
    "titles": {
      "ko": "위플래쉬",
      "en": "Whiplash"
    },
    "releaseYear": 2013,
    "extensions": {
      "ingestChannel": "wikidata_ko_movie",
      "ingestSource": "wikidata_ko"
    }
  }
}
