{
  "wk_000000152": {
    "workId": "wk_000000152",
    "title": "듄",
    "category": "movie",
    "domain": "generalCulture",
    "creator": "Denis Villeneuve",
    "releaseYear": 2021,
    "tags": [
      "영화",
      "대중문화"
    ],
    "legacyIds": [
      "gen_movie_dune-2021_2021"
    ],
    "externalIds": {
      "wikidata": "Q60834962"
    },
    "extensions": {
      "ingestChannel": "manual_wikidata",
      "ingestSource": "manual"
    },
    "qualitySignals": {
      "externalIdVerified": true
    }
  },
  "wk_000001993": {
    "workId": "wk_000001993",
    "title": "조제",
    "category": "movie",
    "domain": "subculture",
    "externalIds": {
      "wikidata": "Q103819225"
    },
    "titles": {
      "ko": "조제",
      "en": "Josée",
      "ja": "ジョゼと虎と魚たち"
    },
    "releaseYear": 2020,
    "extensions": {
      "ingestChannel": "wikidata_ko_movie",
      "ingestSource": "wikidata_ko"
    }
  }
}
