{
  "wk_000000912": {
    "workId": "wk_000000912",
    "title": "Do It Yourself!! -두 잇 유어셀프-",
    "category": "animation",
    "domain": "subculture",
    "externalIds": {
      "wikidata": "Q106189045"
    },
    "titles": {
      "ko": "Do It Yourself!! -두 잇 유어셀프-",
      "en": "Do It Yourself!!",
      "ja": "Do It Yourself!! -どぅー・いっと・ゆあせるふ-"
    },
    "extensions": {
      "ingestChannel": "wikidata_ko_animation",
      "ingestSource": "wikidata_ko"
    }
  },
  "wk_000005139": {
    "workId": "wk_000005139",
    "title": "유리쿠마 아라시",
    "category": "animation",
    "domain": "subculture",
    "externalIds": {
      "wikidata": "Q17602113"
    },
    "titles": {
      "ko": "유리쿠마 아라시",
      "en": "Yurikuma Arashi",
      "ja": "ユリ熊嵐"
    },
    "extensions": {
      "ingestChannel": "wikidata_ko_animation",
      "ingestSource": "wikidata_ko"
    }
  }
}
