{
  "wk_000001331": {
    "workId": "wk_000001331",
    "title": "성검학원의 마검사",
    "category": "animation",
    "domain": "subculture",
    "externalIds": {
      "wikidata": "Q109025546"
    },
    "titles": {
      "ko": "성검학원의 마검사",
      "en": "The Demon Sword Master of Excalibur Academy",
      "ja": "聖剣学院の魔剣使い"
    },
    "extensions": {
      "ingestChannel": "wikidata_ko_animation",
      "ingestSource": "wikidata_ko"
    }
  },
  "wk_000001870": {
    "workId": "wk_000001870",
    "title": "쾌도천사 트윈 엔젤",
    "category": "animation",
    "domain": "subculture",
    "externalIds": {
      "wikidata": "Q1135578"
    },
    "titles": {
      "ko": "쾌도천사 트윈 엔젤",
      "en": "Kaitō Tenshi Twin Angel",
      "ja": "快盗天使ツインエンジェルシリーズ"
    },
    "creator": "Hideyuki Kurata",
    "extensions": {
      "ingestChannel": "wikidata_ko_animation",
      "ingestSource": "wikidata_ko"
    }
  }
}
