{
  "wk_000000441": {
    "workId": "wk_000000441",
    "title": "회복술사의 재시작",
    "category": "manga",
    "domain": "subculture",
    "externalIds": {
      "wikidata": "Q101079461"
    },
    "titles": {
      "en": "Redo of Healer",
      "ja": "回復術士のやり直し",
      "ko": "회복술사의 재시작"
    },
    "creator": "Rui Tsukiyo",
    "extensions": {
      "ingestChannel": "wikidata_manga",
      "ingestSource": "wikidata"
    }
  },
  "wk_000002065": {
    "workId": "wk_000002065",
    "title": "미라클 볼",
    "category": "manga",
    "domain": "subculture",
    "externalIds": {
      "wikidata": "Q11342804"
    },
    "titles": {
      "ko": "미라클 볼",
      "en": "Miracle Ball",
      "ja": "ミラクルボール"
    },
    "creator": "Yasunari Nagatoshi",
    "extensions": {
      "ingestChannel": "wikidata_ko_manga",
      "ingestSource": "wikidata_ko"
    }
  },
  "wk_000002881": {
    "workId": "wk_000002881",
    "title": "이 회사에 좋아하는 사람이 있습니다",
    "category": "manga",
    "domain": "subculture",
    "externalIds": {
      "wikidata": "Q114981464"
    },
    "titles": {
      "ko": "이 회사에 좋아하는 사람이 있습니다",
      "en": "I Have a Crush at Work",
      "ja": "この会社に好きな人がいます"
    },
    "releaseYear": 2019,
    "extensions": {
      "ingestChannel": "wikidata_ko_manga",
      "ingestSource": "wikidata_ko"
    }
  }
}
