{
  "wk_000001037": {
    "workId": "wk_000001037",
    "title": "펭귄의 문제",
    "category": "manga",
    "domain": "subculture",
    "externalIds": {
      "wikidata": "Q1107025"
    },
    "titles": {
      "ko": "펭귄의 문제",
      "en": "A Penguin's Troubles",
      "ja": "ペンギンの問題"
    },
    "creator": "Yūji Nagai",
    "extensions": {
      "ingestChannel": "wikidata_ko_manga",
      "ingestSource": "wikidata_ko"
    }
  },
  "wk_000001354": {
    "workId": "wk_000001354",
    "title": "OH! MY 콘부",
    "category": "manga",
    "domain": "subculture",
    "externalIds": {
      "wikidata": "Q11237135"
    },
    "titles": {
      "ko": "OH! MY 콘부",
      "en": "Oh! My Konbu",
      "ja": "OH!MYコンブ"
    },
    "extensions": {
      "ingestChannel": "wikidata_ko_manga",
      "ingestSource": "wikidata_ko"
    }
  },
  "wk_000003620": {
    "workId": "wk_000003620",
    "title": "푸른하늘 옐",
    "category": "manga",
    "domain": "subculture",
    "externalIds": {
      "wikidata": "Q11662667"
    },
    "titles": {
      "ko": "푸른하늘 옐",
      "en": "Aozora Yell",
      "ja": "青空エール"
    },
    "creator": "Kazune Kawahara",
    "extensions": {
      "ingestChannel": "wikidata_ko_manga",
      "ingestSource": "wikidata_ko"
    }
  }
}
