{
  "wk_000000310": {
    "workId": "wk_000000310",
    "title": "단다단",
    "category": "manga",
    "domain": "subculture",
    "creator": "타츠타 유키",
    "releaseYear": 2021,
    "tags": [
      "오컬트",
      "코미디",
      "액션",
      "로맨스"
    ],
    "externalIds": {
      "tmdb": "240411",
      "wikidata": "Q108069627"
    },
    "legacyIds": [
      "sub_manga_dandadan_2021"
    ],
    "titles": {
      "ko": "단다단",
      "en": "Dandadan",
      "ja": "ダンダダン",
      "romaji": "Dandadan"
    },
    "aliases": [
      "Dandadan",
      "ダンダダン"
    ],
    "extensions": {
      "ingestChannel": "wikidata_manga",
      "ingestSource": "wikidata"
    },
    "qualitySignals": {
      "externalIdVerified": true
    }
  },
  "wk_000000423": {
    "workId": "wk_000000423",
    "title": "낙화유수",
    "category": "manga",
    "domain": "subculture",
    "externalIds": {
      "wikidata": "Q1004281"
    },
    "titles": {
      "en": "Rakka Ryūsui",
      "ja": "落花流水",
      "ko": "낙화유수"
    },
    "releaseYear": 2005,
    "creator": "Ikki Sanada",
    "extensions": {
      "ingestChannel": "wikidata_manga",
      "ingestSource": "wikidata"
    }
  }
}
