{
  "wk_000000258": {
    "workId": "wk_000000258",
    "title": "노 게임 노 라이프",
    "category": "book",
    "domain": "subculture",
    "creator": "카무라",
    "releaseYear": 2011,
    "tags": [
      "라이트노벨",
      "판타지",
      "게임",
      "서브컬처"
    ],
    "legacyIds": [
      "sub_book_no-game-no-life_2011"
    ],
    "titles": {
      "en": "NO Game NO Life",
      "ko": "노 게임 노 라이프"
    },
    "extensions": {
      "coverageSprint03": "legacy_slug",
      "ingestChannel": "manual_wikidata",
      "ingestSource": "manual"
    },
    "externalIds": {
      "wikidata": "Q11325839"
    },
    "qualitySignals": {
      "externalIdVerified": true
    }
  },
  "wk_000002411": {
    "workId": "wk_000002411",
    "title": "프눌과의 전쟁",
    "category": "book",
    "domain": "subculture",
    "externalIds": {
      "wikidata": "Q1056887"
    },
    "titles": {
      "ko": "프눌과의 전쟁",
      "en": "The War with the Fnools"
    },
    "releaseYear": 1964,
    "creator": "フィリップ・K・ディック",
    "extensions": {
      "ingestChannel": "wikidata_ko_book",
      "ingestSource": "wikidata_ko"
    }
  },
  "wk_000003484": {
    "workId": "wk_000003484",
    "title": "지금 지구에 소행성이 돌진해 온다면",
    "category": "book",
    "domain": "subculture",
    "externalIds": {
      "wikidata": "Q107185717"
    },
    "titles": {
      "ko": "지금 지구에 소행성이 돌진해 온다면",
      "en": "Krawumm! Ein Plädoyer für den Weltuntergang"
    },
    "releaseYear": 2012,
    "creator": "Florian Freistetter",
    "extensions": {
      "ingestChannel": "wikidata_ko_book",
      "ingestSource": "wikidata_ko"
    }
  }
}
