{
  "wk_000001439": {
    "workId": "wk_000001439",
    "title": "눈보라 체이스",
    "category": "book",
    "domain": "subculture",
    "externalIds": {
      "wikidata": "Q104189504"
    },
    "titles": {
      "ko": "눈보라 체이스",
      "en": "Q104189504",
      "ja": "雪煙チェイス"
    },
    "creator": "Keigo Higashino",
    "extensions": {
      "ingestChannel": "wikidata_ko_book",
      "ingestSource": "wikidata_ko"
    }
  },
  "wk_000001483": {
    "workId": "wk_000001483",
    "title": "지성개선론",
    "category": "book",
    "domain": "subculture",
    "externalIds": {
      "wikidata": "Q1044508"
    },
    "titles": {
      "ko": "지성개선론",
      "en": "Tractatus de Intellectus Emendatione"
    },
    "releaseYear": 1677,
    "creator": "Benedictus de Spinoza",
    "extensions": {
      "ingestChannel": "wikidata_ko_book",
      "ingestSource": "wikidata_ko"
    }
  },
  "wk_000002250": {
    "workId": "wk_000002250",
    "title": "세계 최고의 암살자, 이세계 귀족으로 전생하다",
    "category": "book",
    "domain": "subculture",
    "externalIds": {
      "wikidata": "Q105519361"
    },
    "titles": {
      "ko": "세계 최고의 암살자, 이세계 귀족으로 전생하다",
      "en": "The World's Finest Assassin Gets Reincarnated in a Different World as an Aristocrat",
      "ja": "世界最高の暗殺者、異世界貴族に転生する"
    },
    "releaseYear": 2024,
    "creator": "Rui Tsukiyo",
    "extensions": {
      "ingestChannel": "wikidata_ko_book",
      "ingestSource": "wikidata_ko"
    }
  },
  "wk_000004099": {
    "workId": "wk_000004099",
    "title": "선종영가집",
    "category": "book",
    "domain": "subculture",
    "externalIds": {
      "wikidata": "Q10825210"
    },
    "titles": {
      "ko": "선종영가집",
      "en": "Essence of Zen Buddhism",
      "ja": "禅宗永嘉集"
    },
    "creator": "Yongjia Xuanjue",
    "extensions": {
      "ingestChannel": "wikidata_ko_book",
      "ingestSource": "wikidata_ko"
    }
  },
  "wk_000004991": {
    "workId": "wk_000004991",
    "title": "점성술 살인사건",
    "category": "book",
    "domain": "subculture",
    "externalIds": {
      "wikidata": "Q10909686"
    },
    "titles": {
      "ko": "점성술 살인사건",
      "en": "The Tokyo Zodiac Murders",
      "ja": "占星術殺人事件"
    },
    "releaseYear": 1981,
    "creator": "島田荘司",
    "extensions": {
      "ingestChannel": "wikidata_ko_book",
      "ingestSource": "wikidata_ko"
    }
  }
}
